create_django_project/__init__.py
create_django_project/_parser.py
create_django_project/config.py
create_django_project/main.py
create_django_project/utils.py
create_django_project-0.0.1.dist-info/entry_points.txt
create_django_project-0.0.1.dist-info/LICENSE
create_django_project-0.0.1.dist-info/WHEEL
create_django_project-0.0.1.dist-info/METADATA
create_django_project-0.0.1.dist-info/RECORD
